{
  "È": "154",
  "ª": "155",
  "Q": "159",
  "!": "300",
  "ü": "310",
  "Ñ": "333",
  "z": "372",
  "á": "400",
  "§": "434",
  "V": "518",
  "W": "550",
  "f": "600",
  "³": "603",
  "ò": "640",
  "û": "644",
  "Í": "647",
  "™": "666",
  "+": "677",
  "Ò": "680",
  "D": "700",
  "Î": "718",
  "\"": "720",
  "…": "728",
  "²": "730",
  "U": "738",
  ";": "745",
  "4": "747",
  "*": "754",
  "ƒ": "758",
  "M": "772",
  "‡": "780",
  "?": "781",
  "Œ": "792",
  "9": "797",
  "1": "798",
  "[": "801",
  "k": "814",
  "Z": "817",
  "~": "819",
  "¤": "820",
  "é": "823",
  "ö": "829",
  "g": "844",
  "Ä": "890",
  "{": "891",
  "ð": "905",
  "%": "912",
  "K": "918",
  "À": "919",
  "ï": "920",
  "\\": "936",
  "¿": "938",
  "S": "939",
  "5": "943",
  "G": "958",
  "x": "959",
  "&": "964",
  "¥": "966",
  "‹": "977",
  "]": "995",
  "Á": "996",
  "¡": "3024",
  "b": "3031",
  "F": "3072",
  "3": "3078",
  "y": "3328",
  "@": "3348",
  "p": "3363",
  "O": "3371",
  "ˆ": "3607",
  "ø": "3609",
  "s": "3713",
  "_": "3721",
  "a": "3747",
  "›": "3765",
  "$": "3766",
  "C": "3770",
  "×": "3805",
  "A": "3808",
  "Š": "3810",
  "#": "3822",
  "—": "3826",
  "Ÿ": "3828",
  "ù": "3829",
  "‰": "3835",
  "’": "3846",
  "I": "3850",
  "ú": "3852",
  "T": "3856",
  "u": "3865"
}
